reddit_decider-1.16.2.dist-info/METADATA
reddit_decider-1.16.2.dist-info/WHEEL
rust_decider/events.py
rust_decider/prometheus_metrics.py
rust_decider/__init__.py
rust_decider/rust_decider.abi3.so
reddit_decider-1.16.2.dist-info/RECORD
