Metadata-Version: 2.1
Name: reddit-decider
Version: 1.16.2
Requires-Dist: prometheus-client ==0.22.1
Requires-Python: >=3.7
